fabricatio_diff-0.2.6.dist-info/METADATA
fabricatio_diff-0.2.6.dist-info/WHEEL
fabricatio_diff/__init__.py
fabricatio_diff/actions/__init__.py
fabricatio_diff/capabilities/__init__.py
fabricatio_diff/capabilities/diff_edit.py
fabricatio_diff/config.py
fabricatio_diff/models/__init__.py
fabricatio_diff/models/diff.py
fabricatio_diff/py.typed
fabricatio_diff/rust.cp312-win_amd64.pyd
fabricatio_diff/rust.pyi
fabricatio_diff/utils.py
fabricatio_diff/workflows/__init__.py
fabricatio_diff-0.2.6.dist-info/RECORD
