Metadata-Version: 2.4
Name: fabricatio-diff
Version: 0.2.6
Classifier: License :: OSI Approved :: MIT License
Classifier: Programming Language :: Python :: 3.12
Classifier: Programming Language :: Python :: 3.13
Classifier: Programming Language :: Python :: 3.14
Classifier: Programming Language :: Python :: Implementation :: CPython
Classifier: Typing :: Typed
Requires-Dist: fabricatio-core
Summary: An extension of fabricatio, which brings up the diff edit capabilities
Author-email: Whth <zettainspector@foxmail.com>
License-Expression: MIT
Requires-Python: >=3.12, <3.15
Project-URL: Homepage, https://github.com/Whth/fabricatio
Project-URL: Repository, https://github.com/Whth/fabricatio
Project-URL: Issues, https://github.com/Whth/fabricatio/issues
